openai_gradio/__init__.py
openai_gradio-0.1.0.dist-info/METADATA
openai_gradio-0.1.0.dist-info/WHEEL
openai_gradio-0.1.0.dist-info/RECORD
