Metadata-Version: 2.3
Name: openai-gradio
Version: 0.1.0
Summary: A Python package for creating Gradio applications with OpenAI models
Project-URL: homepage, https://github.com/your-username/openai-gradio
Project-URL: repository, https://github.com/your-username/openai-gradio
Author-email: Your Name <your.email@example.com>
Classifier: License :: OSI Approved :: MIT License
Classifier: Operating System :: OS Independent
Classifier: Programming Language :: Python :: 3
Requires-Python: >=3.10
Requires-Dist: gradio
Requires-Dist: openai
Provides-Extra: dev
Requires-Dist: pytest; extra == 'dev'
